telegram_django_bot/__init__.py
telegram_django_bot/admin.py
telegram_django_bot/admin_utils.py
telegram_django_bot/apps.py
telegram_django_bot/forms.py
telegram_django_bot/models.py
telegram_django_bot/permissions.py
telegram_django_bot/routing.py
telegram_django_bot/tasks.py
telegram_django_bot/td_viewset.py
telegram_django_bot/telegram_lib_redefinition.py
telegram_django_bot/test.py
telegram_django_bot/tg_dj_bot.py
telegram_django_bot/user_viewset.py
telegram_django_bot/utils.py
telegram_django_bot/locale/ru/LC_MESSAGES/django.mo
telegram_django_bot/locale/ru/LC_MESSAGES/django.po
telegram_django_bot/migrations/0001_initial.py
telegram_django_bot/migrations/0002_delete_user.py
telegram_django_bot/migrations/0003_botmenuelem_message_format.py
telegram_django_bot/migrations/0004_auto_20220915_0448.py
telegram_django_bot/migrations/0005_auto_20221010_1330.py
telegram_django_bot/migrations/0006_auto_20221023_0157.py
telegram_django_bot/migrations/0007_auto_20221202_0305.py
telegram_django_bot/migrations/0008_auto_20221225_1050.py
telegram_django_bot/migrations/__init__.py
telegram_django_bot/templates/dropdown_filter1.html
telegram_django_bot-1.1.0.dist-info/LICENSE
telegram_django_bot-1.1.0.dist-info/METADATA
telegram_django_bot-1.1.0.dist-info/WHEEL
telegram_django_bot-1.1.0.dist-info/top_level.txt
telegram_django_bot-1.1.0.dist-info/RECORD
